py_multitasking/__init__.py
py_multitasking/context.py
py_multitasking/exceptions.py
py_multitasking/helpers.py
py_multitasking/manager.py
py_multitasking/processimpl.py
py_multitasking/task.py
py_multitasking/threadimpl.py
py_multitasking/typedefs.py
py_multitasking/utils.py
py_multitasking-0.1.1.dist-info/LICENSE
py_multitasking-0.1.1.dist-info/METADATA
py_multitasking-0.1.1.dist-info/WHEEL
py_multitasking-0.1.1.dist-info/RECORD
