Metadata-Version: 2.1
Name: py-multitasking
Version: 0.1.1
Summary: Simplify multi tasking with process or thread pool executor.
Author: zimolab
Author-email: zimolab@aliyun.com
Requires-Python: >=3.8,<3.14
Classifier: Programming Language :: Python :: 3
Classifier: Programming Language :: Python :: 3.8
Classifier: Programming Language :: Python :: 3.9
Classifier: Programming Language :: Python :: 3.10
Classifier: Programming Language :: Python :: 3.11
Classifier: Programming Language :: Python :: 3.12
